fetcharxiv/__init__.py
fetcharxiv/main.py
fetcharxiv/webpage.py
fetcharxiv/src/__init__.py
fetcharxiv/src/download.py
fetcharxiv/src/fetch.py
fetcharxiv/src/send_email.py
arXivFans-0.3.1.dist-info/LICENSE
arXivFans-0.3.1.dist-info/METADATA
arXivFans-0.3.1.dist-info/WHEEL
arXivFans-0.3.1.dist-info/entry_points.txt
arXivFans-0.3.1.dist-info/top_level.txt
arXivFans-0.3.1.dist-info/RECORD
